cloudhands/CloudHandsSDK.py
cloudhands/__init__.py
cloudhands/base.py
cloudhands/sdk_types.py
cloudhands/utils.py
cloudhands/version.py
cloudhands-1.0.6.dist-info/METADATA
cloudhands-1.0.6.dist-info/WHEEL
cloudhands-1.0.6.dist-info/top_level.txt
cloudhands-1.0.6.dist-info/RECORD
