Metadata-Version: 2.4
Name: cloudhands
Version: 1.0.6
Summary: Python SDK for CloudHands API
Author: Cloudhands, Inc.
Classifier: Programming Language :: Python :: 3
Classifier: Operating System :: OS Independent
Requires-Python: >=3.6
Requires-Dist: requests>=2.32.3
Dynamic: author
Dynamic: classifier
Dynamic: description
Dynamic: description-content-type
Dynamic: requires-dist
Dynamic: requires-python
Dynamic: summary
